Metadata-Version: 2.1
Name: plusspay-kyc-manager
Version: 1.0.5
Summary: Librería de Plusspay© para la gestión de procesos KYC (Know Your Customer) a través de diferentes proveedores.
Home-page: https://github.com/Pluss-Pay/kyc-didi
Author: Plusspay
Author-email: 
License: MIT
Download-URL: https://github.com/Pluss-Pay/kyc-didi/tarball/1.0.5
Keywords: plusspay
Platform: UNKNOWN
